{
  "EDITOR_STATE": {
    "allProjectFiles": {
      "77823dbc-b8a9-418d-a0df-5ca3303a1d17": {
        "id": "77823dbc-b8a9-418d-a0df-5ca3303a1d17",
        "parent": null,
        "name": "lambda.js",
        "type": "JS_LAMBDA",
        "isDirectory": false,
        "children": [],
        "isRemovable": true,
        "filePath": "lambda.js",
        "cursor": {
          "lineNumber": 2,
          "column": 5
        },
        "config": {
          "runtime": "nodejs10.x",
          "handler": "handler",
          "timeout": 60,
          "memory": 128,
          "layers": []
        },
        "triggers": []
      },
      "07c4edae-6055-4239-810d-7baeaa9e9c63": {
        "id": "07c4edae-6055-4239-810d-7baeaa9e9c63",
        "parent": null,
        "name": "subdir1",
        "type": "DIRECTORY",
        "isDirectory": true,
        "children": [
          "5b2df4ef-e782-4583-93da-cbcc81414666"
        ],
        "isRemovable": true,
        "filePath": "subdir1"
      },
      "5b2df4ef-e782-4583-93da-cbcc81414666": {
        "id": "5b2df4ef-e782-4583-93da-cbcc81414666",
        "parent": "07c4edae-6055-4239-810d-7baeaa9e9c63",
        "name": "new1.js",
        "type": "JS_LAMBDA",
        "isDirectory": false,
        "children": [],
        "isRemovable": true,
        "filePath": "subdir1/new1.js",
        "cursor": {
          "lineNumber": 2,
          "column": 5
        },
        "config": {
          "runtime": "nodejs10.x",
          "handler": "handler",
          "timeout": 60,
          "memory": 128,
          "layers": []
        },
        "triggers": []
      },
      "086fee72-7c95-4dd4-b9d0-14d6e9b862f4": {
        "id": "086fee72-7c95-4dd4-b9d0-14d6e9b862f4",
        "parent": null,
        "name": "new2.js",
        "type": "JS_LAMBDA",
        "isDirectory": false,
        "children": [],
        "isRemovable": true,
        "filePath": "new2.js",
        "cursor": {
          "lineNumber": 2,
          "column": 5
        },
        "config": {
          "runtime": "nodejs10.x",
          "handler": "handler",
          "timeout": 60,
          "memory": 128,
          "layers": []
        },
        "triggers": []
      },
      "30afbb2b-8e6a-426b-b256-2f8314ccaf4e": {
        "id": "30afbb2b-8e6a-426b-b256-2f8314ccaf4e",
        "parent": null,
        "name": "subdir2",
        "type": "DIRECTORY",
        "isDirectory": true,
        "children": [
          "c455c99d-ccf5-4011-9219-e56d8c4cbe1f",
          "05b95bfb-3ccd-4dce-953d-c158f9805948",
          "ce02bb5e-6b4b-4748-be08-f05b3e0412e5"
        ],
        "isRemovable": true,
        "filePath": "subdir2"
      },
      "c455c99d-ccf5-4011-9219-e56d8c4cbe1f": {
        "id": "c455c99d-ccf5-4011-9219-e56d8c4cbe1f",
        "parent": "30afbb2b-8e6a-426b-b256-2f8314ccaf4e",
        "name": "js1.js",
        "type": "JS_FILE",
        "isDirectory": false,
        "children": [],
        "isRemovable": true,
        "filePath": "subdir2/js1.js"
      },
      "05b95bfb-3ccd-4dce-953d-c158f9805948": {
        "id": "05b95bfb-3ccd-4dce-953d-c158f9805948",
        "parent": "30afbb2b-8e6a-426b-b256-2f8314ccaf4e",
        "name": "py1.py",
        "type": "PYTHON_LAMBDA",
        "isDirectory": false,
        "children": [],
        "isRemovable": true,
        "filePath": "subdir2/py1.py",
        "cursor": {
          "lineNumber": 2,
          "column": 5
        },
        "config": {
          "runtime": "python2.7",
          "handler": "handler",
          "timeout": 60,
          "memory": 128,
          "layers": []
        },
        "triggers": []
      },
      "ce02bb5e-6b4b-4748-be08-f05b3e0412e5": {
        "id": "ce02bb5e-6b4b-4748-be08-f05b3e0412e5",
        "parent": "30afbb2b-8e6a-426b-b256-2f8314ccaf4e",
        "name": "__init__.py",
        "type": "PYTHON_FILE",
        "isDirectory": false,
        "children": [],
        "isRemovable": true,
        "filePath": "subdir2/__init__.py"
      },
      "5544f1f0-1528-4970-801d-5f38b7daa9ae": {
        "id": "5544f1f0-1528-4970-801d-5f38b7daa9ae",
        "parent": null,
        "name": "py2.py",
        "type": "PYTHON_LAMBDA",
        "isDirectory": false,
        "children": [],
        "isRemovable": true,
        "filePath": "py2.py",
        "cursor": {
          "lineNumber": 2,
          "column": 5
        },
        "config": {
          "runtime": "python2.7",
          "handler": "handler",
          "timeout": 60,
          "memory": 128,
          "layers": []
        },
        "triggers": []
      }
    },
    "openFiles": [
      "77823dbc-b8a9-418d-a0df-5ca3303a1d17",
      "5b2df4ef-e782-4583-93da-cbcc81414666",
      "086fee72-7c95-4dd4-b9d0-14d6e9b862f4",
      "c455c99d-ccf5-4011-9219-e56d8c4cbe1f",
      "05b95bfb-3ccd-4dce-953d-c158f9805948",
      "5544f1f0-1528-4970-801d-5f38b7daa9ae"
    ],
    "currentFileId": "5544f1f0-1528-4970-801d-5f38b7daa9ae",
    "resources": {},
    "customTemplate": {
      "dialect": null,
      "definitions": null
    },
    "envVariables": [
      {
        "lambdaId": "all",
        "varKey": "SIGMA_AWS_ACC_ID",
        "varValue": null,
        "shouldPersist": false,
        "displayOnly": false,
        "editable": false
      }
    ],
    "packageJSON": {
      "dependencies": {}
    }
  },
  "PROJECT_META": {
    "projectName": "TestRootRepo",
    "projectDescription": "",
    "projectVersion": "1.0.0",
    "projectRegion": "us-east-1",
    "platform": "AWS",
    "language": "nodejs",
    "platformRegions": {},
    "lastSave": 1582617227302
  },
  "VCS_STATE": {
    "provider": "GitHub",
    "repo": {
      "name": "testrootrepo",
      "url": "https://github.com/Kumudikatest/testrootrepo"
    }
  }
}